vnpy_novastrategy/__init__.py
vnpy_novastrategy/backtesting.py
vnpy_novastrategy/base.py
vnpy_novastrategy/engine.py
vnpy_novastrategy/handler.py
vnpy_novastrategy/table.py
vnpy_novastrategy/template.py
vnpy_novastrategy/expression/__init__.py
vnpy_novastrategy/expression/cs_function.py
vnpy_novastrategy/expression/ta_function.py
vnpy_novastrategy/expression/ts_function.py
vnpy_novastrategy/strategies/__init__.py
vnpy_novastrategy/strategies/sma_strategy.py
vnpy_novastrategy/ui/__init__.py
vnpy_novastrategy/ui/nova.ico
vnpy_novastrategy/ui/widget.py
vnpy_novastrategy-0.7.1.dist-info/LICENSE
vnpy_novastrategy-0.7.1.dist-info/METADATA
vnpy_novastrategy-0.7.1.dist-info/WHEEL
vnpy_novastrategy-0.7.1.dist-info/top_level.txt
vnpy_novastrategy-0.7.1.dist-info/RECORD
