Metadata-Version: 2.1
Name: vnpy-novastrategy
Version: 0.7.1
Summary: Nova strategy application for VeighNa quant trading framework.
Home-page: https://www.github.com/veighna-global
Author: VeighNa Global
Author-email: veighna@hotmail.com
License: MIT
Keywords: quant,quantitative,investment,trading,algotrading,crypto,btc
Classifier: Development Status :: 5 - Production/Stable
Classifier: Operating System :: Microsoft :: Windows
Classifier: Operating System :: POSIX :: Linux
Classifier: Operating System :: MacOS
Classifier: Programming Language :: Python :: 3
Classifier: Programming Language :: Python :: 3.10
Classifier: Programming Language :: Python :: 3.11
Classifier: Programming Language :: Python :: 3.12
Classifier: Topic :: Office/Business :: Financial :: Investment
Classifier: Programming Language :: Python :: Implementation :: CPython
Classifier: License :: OSI Approved :: MIT License
Classifier: Natural Language :: English
License-File: LICENSE
Requires-Dist: vnpy-evo
